openap/top/__init__.py
openap/top/base.py
openap/top/climb.py
openap/top/cruise.py
openap/top/descent.py
openap/top/full.py
openap/top/tools.py
openap/top/vis.py
openap_top-1.10.dist-info/METADATA
openap_top-1.10.dist-info/WHEEL
openap_top-1.10.dist-info/licenses/LICENSE
openap_top-1.10.dist-info/RECORD
