Metadata-Version: 2.4
Name: openap-top
Version: 1.10
Summary: Trajectory OPtimizer based on OpenAP model
Project-URL: homepage, https://openap.dev
Project-URL: repository, https://github.com/junzis/openap-top
Project-URL: issues, https://github.com/junzis/openap-top/issues
Author-email: Junzi Sun <git@junzis.com>
License: GNU LGPL v3
License-File: LICENSE
Classifier: Development Status :: 4 - Beta
Classifier: Intended Audience :: Developers
Classifier: Intended Audience :: Information Technology
Classifier: Intended Audience :: Science/Research
Classifier: License :: OSI Approved :: GNU Lesser General Public License v3 (LGPLv3)
Classifier: Programming Language :: Python :: 3
Classifier: Topic :: Software Development :: Libraries :: Python Modules
Requires-Python: >=3.9
Requires-Dist: cartopy>=0.23.0
Requires-Dist: casadi>=3.6
Requires-Dist: openap>=2.4
Requires-Dist: pyproj>=3.4
Requires-Dist: scikit-learn>=1.4.0
Requires-Dist: xarray>=2024.0
